{
  "url": "https://api.github.com/repos/apache/druid/pulls/5632",
  "id": 181058319,
  "node_id": "MDExOlB1bGxSZXF1ZXN0MTgxMDU4MzE5",
  "html_url": "https://github.com/apache/druid/pull/5632",
  "diff_url": "https://github.com/apache/druid/pull/5632.diff",
  "patch_url": "https://github.com/apache/druid/pull/5632.patch",
  "issue_url": "https://api.github.com/repos/apache/druid/issues/5632",
  "number": 5632,
  "state": "closed",
  "locked": false,
  "title": "Fix coordinator loadStatus performance",
  "user": {
    "login": "jon-wei",
    "id": 8729063,
    "node_id": "MDQ6VXNlcjg3MjkwNjM=",
    "avatar_url": "https://avatars.githubusercontent.com/u/8729063?v=4",
    "gravatar_id": "",
    "url": "https://api.github.com/users/jon-wei",
    "html_url": "https://github.com/jon-wei",
    "followers_url": "https://api.github.com/users/jon-wei/followers",
    "following_url": "https://api.github.com/users/jon-wei/following{/other_user}",
    "gists_url": "https://api.github.com/users/jon-wei/gists{/gist_id}",
    "starred_url": "https://api.github.com/users/jon-wei/starred{/owner}{/repo}",
    "subscriptions_url": "https://api.github.com/users/jon-wei/subscriptions",
    "organizations_url": "https://api.github.com/users/jon-wei/orgs",
    "repos_url": "https://api.github.com/users/jon-wei/repos",
    "events_url": "https://api.github.com/users/jon-wei/events{/privacy}",
    "received_events_url": "https://api.github.com/users/jon-wei/received_events",
    "type": "User",
    "site_admin": false
  },
  "body": "`getLoadStatus()` in `DruidCoordinator` determines how many segments need to be loaded per-datasource by retrieving the list of all segments from metadata, then asks each server for its segment inventory and removes the server segments from the set returned from metadata:\r\n\r\n```\r\n      // remove loaded segments\r\n      for (DruidServer druidServer : serverInventoryView.getInventory()) {\r\n        final DruidDataSource loadedView = druidServer.getDataSource(dataSource.getName());\r\n        if (loadedView != null) {\r\n          segments.removeAll(loadedView.getSegments());\r\n        }\r\n      }\r\n```\r\n\r\nThe current code can perform badly when a server has the entire set of segments for a datasource.\r\n\r\nThis is the code for `AbstractSet.removeAll()`:\r\n```\r\n    public boolean removeAll(Collection<?> c) {\r\n        Objects.requireNonNull(c);\r\n        boolean modified = false;\r\n\r\n        if (size() > c.size()) {\r\n            for (Iterator<?> i = c.iterator(); i.hasNext(); )\r\n                modified |= remove(i.next());\r\n        } else {\r\n            for (Iterator<?> i = iterator(); i.hasNext(); ) {\r\n                if (c.contains(i.next())) {\r\n                    i.remove();\r\n                    modified = true;\r\n                }\r\n            }\r\n        }\r\n        return modified;\r\n    }\r\n```\r\n\r\nIn that situation, the else block will be used, and this is a problem because `loadedView.getSegments()` is the values collection of a ConcurrentHashMap, and its contains() method does a full traversal of the map:\r\n\r\n```\r\n  public Collection<DataSegment> getSegments()\r\n  {\r\n    return Collections.unmodifiableCollection(idToSegmentMap.values());\r\n  }\r\n\r\n...\r\n    public static <T> Collection<T> unmodifiableCollection(Collection<? extends T> c) {\r\n        return new UnmodifiableCollection<>(c);\r\n    }\r\n    public boolean contains(Object o)   {return c.contains(o);}\r\n...\r\n    static final class ValuesView<K,V> extends CollectionView<K,V,V>\r\n        implements Collection<V>, java.io.Serializable {\r\n\r\n        ValuesView(ConcurrentHashMap<K,V> map) { super(map); }\r\n\r\n        public final boolean contains(Object o) {\r\n            return map.containsValue(o);\r\n        }\r\n...\r\n    /**\r\n     * Returns {@code true} if this map maps one or more keys to the\r\n     * specified value. Note: This method may require a full traversal\r\n     * of the map, and is much slower than method {@code containsKey}.\r\n     *\r\n     * @param value value whose presence in this map is to be tested\r\n     * @return {@code true} if this map maps one or more keys to the\r\n     *         specified value\r\n     * @throws NullPointerException if the specified value is null\r\n     */\r\n    public boolean containsValue(Object value) {\r\n        if (value == null)\r\n            throw new NullPointerException();\r\n        Node<K,V>[] t;\r\n        if ((t = table) != null) {\r\n            Traverser<K,V> it = new Traverser<K,V>(t, t.length, 0, t.length);\r\n            for (Node<K,V> p; (p = it.advance()) != null; ) {\r\n                V v;\r\n                if ((v = p.val) == value || (v != null && value.equals(v)))\r\n                    return true;\r\n            }\r\n        }\r\n        return false;\r\n    }\r\n...\r\n\r\n```\r\n\r\nThe following benchmark (included in the PR) shows this behavior:\r\n\r\n```\r\nBenchmark                       (serverHasAllSegments)  (totalSegmentsCount)  Mode  Cnt        Score       Error  Units\r\nLoadStatusBenchmark.newVersion                    true                 10000  avgt   50      387.188 \u00b1     4.991  us/op\r\nLoadStatusBenchmark.newVersion                   false                 10000  avgt   50      227.884 \u00b1     2.444  us/op\r\nLoadStatusBenchmark.oldVersion                    true                 10000  avgt   50  1581777.362 \u00b1 38030.835  us/op\r\nLoadStatusBenchmark.oldVersion                   false                 10000  avgt   50      244.024 \u00b1     2.923  us/op\r\n```",
  "created_at": "2018-04-11T23:58:56Z",
  "updated_at": "2018-10-08T22:02:59Z",
  "closed_at": "2018-04-12T22:07:53Z",
  "merged_at": "2018-04-12T22:07:52Z",
  "merge_commit_sha": "e91add6843f7ef9f2ecb6e63e8653064ebf4144c",
  "assignee": null,
  "assignees": [],
  "requested_reviewers": [],
  "requested_teams": [],
  "labels": [
    {
      "id": 120288359,
      "node_id": "MDU6TGFiZWwxMjAyODgzNTk=",
      "url": "https://api.github.com/repos/apache/druid/labels/Performance",
      "name": "Performance",
      "color": "fbca04",
      "default": false,
      "description": null
    },
    {
      "id": 632425053,
      "node_id": "MDU6TGFiZWw2MzI0MjUwNTM=",
      "url": "https://api.github.com/repos/apache/druid/labels/Area%20-%20Segment%20Balancing/Coordination",
      "name": "Area - Segment Balancing/Coordination",
      "color": "fef2c0",
      "default": false,
      "description": null
    }
  ],
  "milestone": {
    "url": "https://api.github.com/repos/apache/druid/milestones/26",
    "html_url": "https://github.com/apache/druid/milestone/26",
    "labels_url": "https://api.github.com/repos/apache/druid/milestones/26/labels",
    "id": 3253774,
    "node_id": "MDk6TWlsZXN0b25lMzI1Mzc3NA==",
    "number": 26,
    "title": "0.12.1",
    "description": "",
    "creator": {
      "login": "gianm",
      "id": 1214075,
      "node_id": "MDQ6VXNlcjEyMTQwNzU=",
      "avatar_url": "https://avatars.githubusercontent.com/u/1214075?v=4",
      "gravatar_id": "",
      "url": "https://api.github.com/users/gianm",
      "html_url": "https://github.com/gianm",
      "followers_url": "https://api.github.com/users/gianm/followers",
      "following_url": "https://api.github.com/users/gianm/following{/other_user}",
      "gists_url": "https://api.github.com/users/gianm/gists{/gist_id}",
      "starred_url": "https://api.github.com/users/gianm/starred{/owner}{/repo}",
      "subscriptions_url": "https://api.github.com/users/gianm/subscriptions",
      "organizations_url": "https://api.github.com/users/gianm/orgs",
      "repos_url": "https://api.github.com/users/gianm/repos",
      "events_url": "https://api.github.com/users/gianm/events{/privacy}",
      "received_events_url": "https://api.github.com/users/gianm/received_events",
      "type": "User",
      "site_admin": false
    },
    "open_issues": 0,
    "closed_issues": 63,
    "state": "closed",
    "created_at": "2018-04-09T19:19:05Z",
    "updated_at": "2018-10-08T22:02:59Z",
    "due_on": null,
    "closed_at": "2018-07-03T20:20:16Z"
  },
  "draft": false,
  "commits_url": "https://api.github.com/repos/apache/druid/pulls/5632/commits",
  "review_comments_url": "https://api.github.com/repos/apache/druid/pulls/5632/comments",
  "review_comment_url": "https://api.github.com/repos/apache/druid/pulls/comments{/number}",
  "comments_url": "https://api.github.com/repos/apache/druid/issues/5632/comments",
  "statuses_url": "https://api.github.com/repos/apache/druid/statuses/c9c17751c7e6e9a0f089a1aafdca527f0ffcb318",
  "head": {
    "label": "jon-wei:loadstatus_fix",
    "ref": "loadstatus_fix",
    "sha": "c9c17751c7e6e9a0f089a1aafdca527f0ffcb318",
    "user": {
      "login": "jon-wei",
      "id": 8729063,
      "node_id": "MDQ6VXNlcjg3MjkwNjM=",
      "avatar_url": "https://avatars.githubusercontent.com/u/8729063?v=4",
      "gravatar_id": "",
      "url": "https://api.github.com/users/jon-wei",
      "html_url": "https://github.com/jon-wei",
      "followers_url": "https://api.github.com/users/jon-wei/followers",
      "following_url": "https://api.github.com/users/jon-wei/following{/other_user}",
      "gists_url": "https://api.github.com/users/jon-wei/gists{/gist_id}",
      "starred_url": "https://api.github.com/users/jon-wei/starred{/owner}{/repo}",
      "subscriptions_url": "https://api.github.com/users/jon-wei/subscriptions",
      "organizations_url": "https://api.github.com/users/jon-wei/orgs",
      "repos_url": "https://api.github.com/users/jon-wei/repos",
      "events_url": "https://api.github.com/users/jon-wei/events{/privacy}",
      "received_events_url": "https://api.github.com/users/jon-wei/received_events",
      "type": "User",
      "site_admin": false
    },
    "repo": {
      "id": 41450391,
      "node_id": "MDEwOlJlcG9zaXRvcnk0MTQ1MDM5MQ==",
      "name": "druid",
      "full_name": "jon-wei/druid",
      "private": false,
      "owner": {
        "login": "jon-wei",
        "id": 8729063,
        "node_id": "MDQ6VXNlcjg3MjkwNjM=",
        "avatar_url": "https://avatars.githubusercontent.com/u/8729063?v=4",
        "gravatar_id": "",
        "url": "https://api.github.com/users/jon-wei",
        "html_url": "https://github.com/jon-wei",
        "followers_url": "https://api.github.com/users/jon-wei/followers",
        "following_url": "https://api.github.com/users/jon-wei/following{/other_user}",
        "gists_url": "https://api.github.com/users/jon-wei/gists{/gist_id}",
        "starred_url": "https://api.github.com/users/jon-wei/starred{/owner}{/repo}",
        "subscriptions_url": "https://api.github.com/users/jon-wei/subscriptions",
        "organizations_url": "https://api.github.com/users/jon-wei/orgs",
        "repos_url": "https://api.github.com/users/jon-wei/repos",
        "events_url": "https://api.github.com/users/jon-wei/events{/privacy}",
        "received_events_url": "https://api.github.com/users/jon-wei/received_events",
        "type": "User",
        "site_admin": false
      },
      "html_url": "https://github.com/jon-wei/druid",
      "description": "Column oriented distributed data store ideal for powering interactive applications",
      "fork": true,
      "url": "https://api.github.com/repos/jon-wei/druid",
      "forks_url": "https://api.github.com/repos/jon-wei/druid/forks",
      "keys_url": "https://api.github.com/repos/jon-wei/druid/keys{/key_id}",
      "collaborators_url": "https://api.github.com/repos/jon-wei/druid/collaborators{/collaborator}",
      "teams_url": "https://api.github.com/repos/jon-wei/druid/teams",
      "hooks_url": "https://api.github.com/repos/jon-wei/druid/hooks",
      "issue_events_url": "https://api.github.com/repos/jon-wei/druid/issues/events{/number}",
      "events_url": "https://api.github.com/repos/jon-wei/druid/events",
      "assignees_url": "https://api.github.com/repos/jon-wei/druid/assignees{/user}",
      "branches_url": "https://api.github.com/repos/jon-wei/druid/branches{/branch}",
      "tags_url": "https://api.github.com/repos/jon-wei/druid/tags",
      "blobs_url": "https://api.github.com/repos/jon-wei/druid/git/blobs{/sha}",
      "git_tags_url": "https://api.github.com/repos/jon-wei/druid/git/tags{/sha}",
      "git_refs_url": "https://api.github.com/repos/jon-wei/druid/git/refs{/sha}",
      "trees_url": "https://api.github.com/repos/jon-wei/druid/git/trees{/sha}",
      "statuses_url": "https://api.github.com/repos/jon-wei/druid/statuses/{sha}",
      "languages_url": "https://api.github.com/repos/jon-wei/druid/languages",
      "stargazers_url": "https://api.github.com/repos/jon-wei/druid/stargazers",
      "contributors_url": "https://api.github.com/repos/jon-wei/druid/contributors",
      "subscribers_url": "https://api.github.com/repos/jon-wei/druid/subscribers",
      "subscription_url": "https://api.github.com/repos/jon-wei/druid/subscription",
      "commits_url": "https://api.github.com/repos/jon-wei/druid/commits{/sha}",
      "git_commits_url": "https://api.github.com/repos/jon-wei/druid/git/commits{/sha}",
      "comments_url": "https://api.github.com/repos/jon-wei/druid/comments{/number}",
      "issue_comment_url": "https://api.github.com/repos/jon-wei/druid/issues/comments{/number}",
      "contents_url": "https://api.github.com/repos/jon-wei/druid/contents/{+path}",
      "compare_url": "https://api.github.com/repos/jon-wei/druid/compare/{base}...{head}",
      "merges_url": "https://api.github.com/repos/jon-wei/druid/merges",
      "archive_url": "https://api.github.com/repos/jon-wei/druid/{archive_format}{/ref}",
      "downloads_url": "https://api.github.com/repos/jon-wei/druid/downloads",
      "issues_url": "https://api.github.com/repos/jon-wei/druid/issues{/number}",
      "pulls_url": "https://api.github.com/repos/jon-wei/druid/pulls{/number}",
      "milestones_url": "https://api.github.com/repos/jon-wei/druid/milestones{/number}",
      "notifications_url": "https://api.github.com/repos/jon-wei/druid/notifications{?since,all,participating}",
      "labels_url": "https://api.github.com/repos/jon-wei/druid/labels{/name}",
      "releases_url": "https://api.github.com/repos/jon-wei/druid/releases{/id}",
      "deployments_url": "https://api.github.com/repos/jon-wei/druid/deployments",
      "created_at": "2015-08-26T21:18:05Z",
      "updated_at": "2021-03-08T21:47:50Z",
      "pushed_at": "2022-11-02T10:30:30Z",
      "git_url": "git://github.com/jon-wei/druid.git",
      "ssh_url": "git@github.com:jon-wei/druid.git",
      "clone_url": "https://github.com/jon-wei/druid.git",
      "svn_url": "https://github.com/jon-wei/druid",
      "homepage": "http://druid.io",
      "size": 282376,
      "stargazers_count": 0,
      "watchers_count": 0,
      "language": "Java",
      "has_issues": false,
      "has_projects": true,
      "has_downloads": true,
      "has_wiki": true,
      "has_pages": false,
      "has_discussions": false,
      "forks_count": 0,
      "mirror_url": null,
      "archived": false,
      "disabled": false,
      "open_issues_count": 0,
      "license": {
        "key": "apache-2.0",
        "name": "Apache License 2.0",
        "spdx_id": "Apache-2.0",
        "url": "https://api.github.com/licenses/apache-2.0",
        "node_id": "MDc6TGljZW5zZTI="
      },
      "allow_forking": true,
      "is_template": false,
      "web_commit_signoff_required": false,
      "topics": [],
      "visibility": "public",
      "forks": 0,
      "open_issues": 0,
      "watchers": 0,
      "default_branch": "master"
    }
  },
  "base": {
    "label": "apache:master",
    "ref": "master",
    "sha": "afa75e04b779a651abffd2f4f272f2afb07fdeea",
    "user": {
      "login": "apache",
      "id": 47359,
      "node_id": "MDEyOk9yZ2FuaXphdGlvbjQ3MzU5",
      "avatar_url": "https://avatars.githubusercontent.com/u/47359?v=4",
      "gravatar_id": "",
      "url": "https://api.github.com/users/apache",
      "html_url": "https://github.com/apache",
      "followers_url": "https://api.github.com/users/apache/followers",
      "following_url": "https://api.github.com/users/apache/following{/other_user}",
      "gists_url": "https://api.github.com/users/apache/gists{/gist_id}",
      "starred_url": "https://api.github.com/users/apache/starred{/owner}{/repo}",
      "subscriptions_url": "https://api.github.com/users/apache/subscriptions",
      "organizations_url": "https://api.github.com/users/apache/orgs",
      "repos_url": "https://api.github.com/users/apache/repos",
      "events_url": "https://api.github.com/users/apache/events{/privacy}",
      "received_events_url": "https://api.github.com/users/apache/received_events",
      "type": "Organization",
      "site_admin": false
    },
    "repo": {
      "id": 6358188,
      "node_id": "MDEwOlJlcG9zaXRvcnk2MzU4MTg4",
      "name": "druid",
      "full_name": "apache/druid",
      "private": false,
      "owner": {
        "login": "apache",
        "id": 47359,
        "node_id": "MDEyOk9yZ2FuaXphdGlvbjQ3MzU5",
        "avatar_url": "https://avatars.githubusercontent.com/u/47359?v=4",
        "gravatar_id": "",
        "url": "https://api.github.com/users/apache",
        "html_url": "https://github.com/apache",
        "followers_url": "https://api.github.com/users/apache/followers",
        "following_url": "https://api.github.com/users/apache/following{/other_user}",
        "gists_url": "https://api.github.com/users/apache/gists{/gist_id}",
        "starred_url": "https://api.github.com/users/apache/starred{/owner}{/repo}",
        "subscriptions_url": "https://api.github.com/users/apache/subscriptions",
        "organizations_url": "https://api.github.com/users/apache/orgs",
        "repos_url": "https://api.github.com/users/apache/repos",
        "events_url": "https://api.github.com/users/apache/events{/privacy}",
        "received_events_url": "https://api.github.com/users/apache/received_events",
        "type": "Organization",
        "site_admin": false
      },
      "html_url": "https://github.com/apache/druid",
      "description": "Apache Druid: a high performance real-time analytics database.",
      "fork": false,
      "url": "https://api.github.com/repos/apache/druid",
      "forks_url": "https://api.github.com/repos/apache/druid/forks",
      "keys_url": "https://api.github.com/repos/apache/druid/keys{/key_id}",
      "collaborators_url": "https://api.github.com/repos/apache/druid/collaborators{/collaborator}",
      "teams_url": "https://api.github.com/repos/apache/druid/teams",
      "hooks_url": "https://api.github.com/repos/apache/druid/hooks",
      "issue_events_url": "https://api.github.com/repos/apache/druid/issues/events{/number}",
      "events_url": "https://api.github.com/repos/apache/druid/events",
      "assignees_url": "https://api.github.com/repos/apache/druid/assignees{/user}",
      "branches_url": "https://api.github.com/repos/apache/druid/branches{/branch}",
      "tags_url": "https://api.github.com/repos/apache/druid/tags",
      "blobs_url": "https://api.github.com/repos/apache/druid/git/blobs{/sha}",
      "git_tags_url": "https://api.github.com/repos/apache/druid/git/tags{/sha}",
      "git_refs_url": "https://api.github.com/repos/apache/druid/git/refs{/sha}",
      "trees_url": "https://api.github.com/repos/apache/druid/git/trees{/sha}",
      "statuses_url": "https://api.github.com/repos/apache/druid/statuses/{sha}",
      "languages_url": "https://api.github.com/repos/apache/druid/languages",
      "stargazers_url": "https://api.github.com/repos/apache/druid/stargazers",
      "contributors_url": "https://api.github.com/repos/apache/druid/contributors",
      "subscribers_url": "https://api.github.com/repos/apache/druid/subscribers",
      "subscription_url": "https://api.github.com/repos/apache/druid/subscription",
      "commits_url": "https://api.github.com/repos/apache/druid/commits{/sha}",
      "git_commits_url": "https://api.github.com/repos/apache/druid/git/commits{/sha}",
      "comments_url": "https://api.github.com/repos/apache/druid/comments{/number}",
      "issue_comment_url": "https://api.github.com/repos/apache/druid/issues/comments{/number}",
      "contents_url": "https://api.github.com/repos/apache/druid/contents/{+path}",
      "compare_url": "https://api.github.com/repos/apache/druid/compare/{base}...{head}",
      "merges_url": "https://api.github.com/repos/apache/druid/merges",
      "archive_url": "https://api.github.com/repos/apache/druid/{archive_format}{/ref}",
      "downloads_url": "https://api.github.com/repos/apache/druid/downloads",
      "issues_url": "https://api.github.com/repos/apache/druid/issues{/number}",
      "pulls_url": "https://api.github.com/repos/apache/druid/pulls{/number}",
      "milestones_url": "https://api.github.com/repos/apache/druid/milestones{/number}",
      "notifications_url": "https://api.github.com/repos/apache/druid/notifications{?since,all,participating}",
      "labels_url": "https://api.github.com/repos/apache/druid/labels{/name}",
      "releases_url": "https://api.github.com/repos/apache/druid/releases{/id}",
      "deployments_url": "https://api.github.com/repos/apache/druid/deployments",
      "created_at": "2012-10-23T19:08:07Z",
      "updated_at": "2022-12-26T05:51:26Z",
      "pushed_at": "2022-12-23T15:15:30Z",
      "git_url": "git://github.com/apache/druid.git",
      "ssh_url": "git@github.com:apache/druid.git",
      "clone_url": "https://github.com/apache/druid.git",
      "svn_url": "https://github.com/apache/druid",
      "homepage": "https://druid.apache.org/",
      "size": 294251,
      "stargazers_count": 12288,
      "watchers_count": 12288,
      "language": "Java",
      "has_issues": true,
      "has_projects": true,
      "has_downloads": true,
      "has_wiki": true,
      "has_pages": false,
      "has_discussions": false,
      "forks_count": 3408,
      "mirror_url": null,
      "archived": false,
      "disabled": false,
      "open_issues_count": 1607,
      "license": {
        "key": "apache-2.0",
        "name": "Apache License 2.0",
        "spdx_id": "Apache-2.0",
        "url": "https://api.github.com/licenses/apache-2.0",
        "node_id": "MDc6TGljZW5zZTI="
      },
      "allow_forking": true,
      "is_template": false,
      "web_commit_signoff_required": false,
      "topics": [
        "druid"
      ],
      "visibility": "public",
      "forks": 3408,
      "open_issues": 1607,
      "watchers": 12288,
      "default_branch": "master"
    }
  },
  "_links": {
    "self": {
      "href": "https://api.github.com/repos/apache/druid/pulls/5632"
    },
    "html": {
      "href": "https://github.com/apache/druid/pull/5632"
    },
    "issue": {
      "href": "https://api.github.com/repos/apache/druid/issues/5632"
    },
    "comments": {
      "href": "https://api.github.com/repos/apache/druid/issues/5632/comments"
    },
    "review_comments": {
      "href": "https://api.github.com/repos/apache/druid/pulls/5632/comments"
    },
    "review_comment": {
      "href": "https://api.github.com/repos/apache/druid/pulls/comments{/number}"
    },
    "commits": {
      "href": "https://api.github.com/repos/apache/druid/pulls/5632/commits"
    },
    "statuses": {
      "href": "https://api.github.com/repos/apache/druid/statuses/c9c17751c7e6e9a0f089a1aafdca527f0ffcb318"
    }
  },
  "author_association": "CONTRIBUTOR",
  "auto_merge": null,
  "active_lock_reason": null,
  "merged": true,
  "mergeable": null,
  "rebaseable": null,
  "mergeable_state": "unknown",
  "merged_by": {
    "login": "jon-wei",
    "id": 8729063,
    "node_id": "MDQ6VXNlcjg3MjkwNjM=",
    "avatar_url": "https://avatars.githubusercontent.com/u/8729063?v=4",
    "gravatar_id": "",
    "url": "https://api.github.com/users/jon-wei",
    "html_url": "https://github.com/jon-wei",
    "followers_url": "https://api.github.com/users/jon-wei/followers",
    "following_url": "https://api.github.com/users/jon-wei/following{/other_user}",
    "gists_url": "https://api.github.com/users/jon-wei/gists{/gist_id}",
    "starred_url": "https://api.github.com/users/jon-wei/starred{/owner}{/repo}",
    "subscriptions_url": "https://api.github.com/users/jon-wei/subscriptions",
    "organizations_url": "https://api.github.com/users/jon-wei/orgs",
    "repos_url": "https://api.github.com/users/jon-wei/repos",
    "events_url": "https://api.github.com/users/jon-wei/events{/privacy}",
    "received_events_url": "https://api.github.com/users/jon-wei/received_events",
    "type": "User",
    "site_admin": false
  },
  "comments": 3,
  "review_comments": 2,
  "maintainer_can_modify": false,
  "commits": 6,
  "additions": 126,
  "deletions": 1,
  "changed_files": 2
}