{
  "url": "https://api.github.com/repos/apache/bookkeeper/pulls/888",
  "id": 159155047,
  "node_id": "MDExOlB1bGxSZXF1ZXN0MTU5MTU1MDQ3",
  "html_url": "https://github.com/apache/bookkeeper/pull/888",
  "diff_url": "https://github.com/apache/bookkeeper/pull/888.diff",
  "patch_url": "https://github.com/apache/bookkeeper/pull/888.patch",
  "issue_url": "https://api.github.com/repos/apache/bookkeeper/issues/888",
  "number": 888,
  "state": "closed",
  "locked": false,
  "title": "Rework of binary distribution licenses",
  "user": {
    "login": "ivankelly",
    "id": 54955,
    "node_id": "MDQ6VXNlcjU0OTU1",
    "avatar_url": "https://avatars.githubusercontent.com/u/54955?v=4",
    "gravatar_id": "",
    "url": "https://api.github.com/users/ivankelly",
    "html_url": "https://github.com/ivankelly",
    "followers_url": "https://api.github.com/users/ivankelly/followers",
    "following_url": "https://api.github.com/users/ivankelly/following{/other_user}",
    "gists_url": "https://api.github.com/users/ivankelly/gists{/gist_id}",
    "starred_url": "https://api.github.com/users/ivankelly/starred{/owner}{/repo}",
    "subscriptions_url": "https://api.github.com/users/ivankelly/subscriptions",
    "organizations_url": "https://api.github.com/users/ivankelly/orgs",
    "repos_url": "https://api.github.com/users/ivankelly/repos",
    "events_url": "https://api.github.com/users/ivankelly/events{/privacy}",
    "received_events_url": "https://api.github.com/users/ivankelly/received_events",
    "type": "User",
    "site_admin": false
  },
  "body": "All redistributed jars are mentioned in the LICENSE file. If the jar\r\nis ASLv2, it is simply listed under the ASLv2 text. If these ASLv2\r\njars have their own NOTICE files, then the relevant portions are added\r\nto our NOTICE file.\r\n\r\nAll jar under license other than ASLv2 get their own section in\r\nLICENSE, which links to the full text of their license. Non-ASLv2\r\ngenerally do not require an update to NOTICE.\r\n\r\nThis change also includes a script, check-binary-license, which checks\r\nthat the contents on the LICENSE and NOTICE actually matches what\r\nbundled in the distribution tarball.\r\n",
  "created_at": "2017-12-19T12:31:21Z",
  "updated_at": "2018-01-18T19:01:53Z",
  "closed_at": "2018-01-18T19:01:17Z",
  "merged_at": null,
  "merge_commit_sha": "0115a91f00a734285bc17eaf9277b2d6a218ffe1",
  "assignee": {
    "login": "ivankelly",
    "id": 54955,
    "node_id": "MDQ6VXNlcjU0OTU1",
    "avatar_url": "https://avatars.githubusercontent.com/u/54955?v=4",
    "gravatar_id": "",
    "url": "https://api.github.com/users/ivankelly",
    "html_url": "https://github.com/ivankelly",
    "followers_url": "https://api.github.com/users/ivankelly/followers",
    "following_url": "https://api.github.com/users/ivankelly/following{/other_user}",
    "gists_url": "https://api.github.com/users/ivankelly/gists{/gist_id}",
    "starred_url": "https://api.github.com/users/ivankelly/starred{/owner}{/repo}",
    "subscriptions_url": "https://api.github.com/users/ivankelly/subscriptions",
    "organizations_url": "https://api.github.com/users/ivankelly/orgs",
    "repos_url": "https://api.github.com/users/ivankelly/repos",
    "events_url": "https://api.github.com/users/ivankelly/events{/privacy}",
    "received_events_url": "https://api.github.com/users/ivankelly/received_events",
    "type": "User",
    "site_admin": false
  },
  "assignees": [
    {
      "login": "ivankelly",
      "id": 54955,
      "node_id": "MDQ6VXNlcjU0OTU1",
      "avatar_url": "https://avatars.githubusercontent.com/u/54955?v=4",
      "gravatar_id": "",
      "url": "https://api.github.com/users/ivankelly",
      "html_url": "https://github.com/ivankelly",
      "followers_url": "https://api.github.com/users/ivankelly/followers",
      "following_url": "https://api.github.com/users/ivankelly/following{/other_user}",
      "gists_url": "https://api.github.com/users/ivankelly/gists{/gist_id}",
      "starred_url": "https://api.github.com/users/ivankelly/starred{/owner}{/repo}",
      "subscriptions_url": "https://api.github.com/users/ivankelly/subscriptions",
      "organizations_url": "https://api.github.com/users/ivankelly/orgs",
      "repos_url": "https://api.github.com/users/ivankelly/repos",
      "events_url": "https://api.github.com/users/ivankelly/events{/privacy}",
      "received_events_url": "https://api.github.com/users/ivankelly/received_events",
      "type": "User",
      "site_admin": false
    }
  ],
  "requested_reviewers": [
    {
      "login": "merlimat",
      "id": 62500,
      "node_id": "MDQ6VXNlcjYyNTAw",
      "avatar_url": "https://avatars.githubusercontent.com/u/62500?v=4",
      "gravatar_id": "",
      "url": "https://api.github.com/users/merlimat",
      "html_url": "https://github.com/merlimat",
      "followers_url": "https://api.github.com/users/merlimat/followers",
      "following_url": "https://api.github.com/users/merlimat/following{/other_user}",
      "gists_url": "https://api.github.com/users/merlimat/gists{/gist_id}",
      "starred_url": "https://api.github.com/users/merlimat/starred{/owner}{/repo}",
      "subscriptions_url": "https://api.github.com/users/merlimat/subscriptions",
      "organizations_url": "https://api.github.com/users/merlimat/orgs",
      "repos_url": "https://api.github.com/users/merlimat/repos",
      "events_url": "https://api.github.com/users/merlimat/events{/privacy}",
      "received_events_url": "https://api.github.com/users/merlimat/received_events",
      "type": "User",
      "site_admin": false
    },
    {
      "login": "jiazhai",
      "id": 6348208,
      "node_id": "MDQ6VXNlcjYzNDgyMDg=",
      "avatar_url": "https://avatars.githubusercontent.com/u/6348208?v=4",
      "gravatar_id": "",
      "url": "https://api.github.com/users/jiazhai",
      "html_url": "https://github.com/jiazhai",
      "followers_url": "https://api.github.com/users/jiazhai/followers",
      "following_url": "https://api.github.com/users/jiazhai/following{/other_user}",
      "gists_url": "https://api.github.com/users/jiazhai/gists{/gist_id}",
      "starred_url": "https://api.github.com/users/jiazhai/starred{/owner}{/repo}",
      "subscriptions_url": "https://api.github.com/users/jiazhai/subscriptions",
      "organizations_url": "https://api.github.com/users/jiazhai/orgs",
      "repos_url": "https://api.github.com/users/jiazhai/repos",
      "events_url": "https://api.github.com/users/jiazhai/events{/privacy}",
      "received_events_url": "https://api.github.com/users/jiazhai/received_events",
      "type": "User",
      "site_admin": false
    },
    {
      "login": "eolivelli",
      "id": 9469110,
      "node_id": "MDQ6VXNlcjk0NjkxMTA=",
      "avatar_url": "https://avatars.githubusercontent.com/u/9469110?v=4",
      "gravatar_id": "",
      "url": "https://api.github.com/users/eolivelli",
      "html_url": "https://github.com/eolivelli",
      "followers_url": "https://api.github.com/users/eolivelli/followers",
      "following_url": "https://api.github.com/users/eolivelli/following{/other_user}",
      "gists_url": "https://api.github.com/users/eolivelli/gists{/gist_id}",
      "starred_url": "https://api.github.com/users/eolivelli/starred{/owner}{/repo}",
      "subscriptions_url": "https://api.github.com/users/eolivelli/subscriptions",
      "organizations_url": "https://api.github.com/users/eolivelli/orgs",
      "repos_url": "https://api.github.com/users/eolivelli/repos",
      "events_url": "https://api.github.com/users/eolivelli/events{/privacy}",
      "received_events_url": "https://api.github.com/users/eolivelli/received_events",
      "type": "User",
      "site_admin": false
    }
  ],
  "requested_teams": [],
  "labels": [
    {
      "id": 636301220,
      "node_id": "MDU6TGFiZWw2MzYzMDEyMjA=",
      "url": "https://api.github.com/repos/apache/bookkeeper/labels/type/task",
      "name": "type/task",
      "color": "d4ccff",
      "default": false,
      "description": ""
    },
    {
      "id": 657286581,
      "node_id": "MDU6TGFiZWw2NTcyODY1ODE=",
      "url": "https://api.github.com/repos/apache/bookkeeper/labels/area/release",
      "name": "area/release",
      "color": "5319e7",
      "default": false,
      "description": ""
    },
    {
      "id": 740113030,
      "node_id": "MDU6TGFiZWw3NDAxMTMwMzA=",
      "url": "https://api.github.com/repos/apache/bookkeeper/labels/release/4.7.0",
      "name": "release/4.7.0",
      "color": "1d76db",
      "default": false,
      "description": null
    }
  ],
  "milestone": {
    "url": "https://api.github.com/repos/apache/bookkeeper/milestones/3",
    "html_url": "https://github.com/apache/bookkeeper/milestone/3",
    "labels_url": "https://api.github.com/repos/apache/bookkeeper/milestones/3/labels",
    "id": 2887234,
    "node_id": "MDk6TWlsZXN0b25lMjg4NzIzNA==",
    "number": 3,
    "title": "4.7.0",
    "description": "Release 4.7.0",
    "creator": {
      "login": "jiazhai",
      "id": 6348208,
      "node_id": "MDQ6VXNlcjYzNDgyMDg=",
      "avatar_url": "https://avatars.githubusercontent.com/u/6348208?v=4",
      "gravatar_id": "",
      "url": "https://api.github.com/users/jiazhai",
      "html_url": "https://github.com/jiazhai",
      "followers_url": "https://api.github.com/users/jiazhai/followers",
      "following_url": "https://api.github.com/users/jiazhai/following{/other_user}",
      "gists_url": "https://api.github.com/users/jiazhai/gists{/gist_id}",
      "starred_url": "https://api.github.com/users/jiazhai/starred{/owner}{/repo}",
      "subscriptions_url": "https://api.github.com/users/jiazhai/subscriptions",
      "organizations_url": "https://api.github.com/users/jiazhai/orgs",
      "repos_url": "https://api.github.com/users/jiazhai/repos",
      "events_url": "https://api.github.com/users/jiazhai/events{/privacy}",
      "received_events_url": "https://api.github.com/users/jiazhai/received_events",
      "type": "User",
      "site_admin": false
    },
    "open_issues": 0,
    "closed_issues": 446,
    "state": "closed",
    "created_at": "2017-11-04T00:04:40Z",
    "updated_at": "2018-04-19T07:06:51Z",
    "due_on": "2018-04-16T07:00:00Z",
    "closed_at": "2018-04-17T07:43:51Z"
  },
  "draft": false,
  "commits_url": "https://api.github.com/repos/apache/bookkeeper/pulls/888/commits",
  "review_comments_url": "https://api.github.com/repos/apache/bookkeeper/pulls/888/comments",
  "review_comment_url": "https://api.github.com/repos/apache/bookkeeper/pulls/comments{/number}",
  "comments_url": "https://api.github.com/repos/apache/bookkeeper/issues/888/comments",
  "statuses_url": "https://api.github.com/repos/apache/bookkeeper/statuses/e1c8d6edfc3f31f6a95195f72594d383011b8de9",
  "head": {
    "label": "ivankelly:license-rework",
    "ref": "license-rework",
    "sha": "e1c8d6edfc3f31f6a95195f72594d383011b8de9",
    "user": {
      "login": "ivankelly",
      "id": 54955,
      "node_id": "MDQ6VXNlcjU0OTU1",
      "avatar_url": "https://avatars.githubusercontent.com/u/54955?v=4",
      "gravatar_id": "",
      "url": "https://api.github.com/users/ivankelly",
      "html_url": "https://github.com/ivankelly",
      "followers_url": "https://api.github.com/users/ivankelly/followers",
      "following_url": "https://api.github.com/users/ivankelly/following{/other_user}",
      "gists_url": "https://api.github.com/users/ivankelly/gists{/gist_id}",
      "starred_url": "https://api.github.com/users/ivankelly/starred{/owner}{/repo}",
      "subscriptions_url": "https://api.github.com/users/ivankelly/subscriptions",
      "organizations_url": "https://api.github.com/users/ivankelly/orgs",
      "repos_url": "https://api.github.com/users/ivankelly/repos",
      "events_url": "https://api.github.com/users/ivankelly/events{/privacy}",
      "received_events_url": "https://api.github.com/users/ivankelly/received_events",
      "type": "User",
      "site_admin": false
    },
    "repo": {
      "id": 1587510,
      "node_id": "MDEwOlJlcG9zaXRvcnkxNTg3NTEw",
      "name": "bookkeeper",
      "full_name": "ivankelly/bookkeeper",
      "private": false,
      "owner": {
        "login": "ivankelly",
        "id": 54955,
        "node_id": "MDQ6VXNlcjU0OTU1",
        "avatar_url": "https://avatars.githubusercontent.com/u/54955?v=4",
        "gravatar_id": "",
        "url": "https://api.github.com/users/ivankelly",
        "html_url": "https://github.com/ivankelly",
        "followers_url": "https://api.github.com/users/ivankelly/followers",
        "following_url": "https://api.github.com/users/ivankelly/following{/other_user}",
        "gists_url": "https://api.github.com/users/ivankelly/gists{/gist_id}",
        "starred_url": "https://api.github.com/users/ivankelly/starred{/owner}{/repo}",
        "subscriptions_url": "https://api.github.com/users/ivankelly/subscriptions",
        "organizations_url": "https://api.github.com/users/ivankelly/orgs",
        "repos_url": "https://api.github.com/users/ivankelly/repos",
        "events_url": "https://api.github.com/users/ivankelly/events{/privacy}",
        "received_events_url": "https://api.github.com/users/ivankelly/received_events",
        "type": "User",
        "site_admin": false
      },
      "html_url": "https://github.com/ivankelly/bookkeeper",
      "description": "Mirror of Apache Bookkeeper",
      "fork": true,
      "url": "https://api.github.com/repos/ivankelly/bookkeeper",
      "forks_url": "https://api.github.com/repos/ivankelly/bookkeeper/forks",
      "keys_url": "https://api.github.com/repos/ivankelly/bookkeeper/keys{/key_id}",
      "collaborators_url": "https://api.github.com/repos/ivankelly/bookkeeper/collaborators{/collaborator}",
      "teams_url": "https://api.github.com/repos/ivankelly/bookkeeper/teams",
      "hooks_url": "https://api.github.com/repos/ivankelly/bookkeeper/hooks",
      "issue_events_url": "https://api.github.com/repos/ivankelly/bookkeeper/issues/events{/number}",
      "events_url": "https://api.github.com/repos/ivankelly/bookkeeper/events",
      "assignees_url": "https://api.github.com/repos/ivankelly/bookkeeper/assignees{/user}",
      "branches_url": "https://api.github.com/repos/ivankelly/bookkeeper/branches{/branch}",
      "tags_url": "https://api.github.com/repos/ivankelly/bookkeeper/tags",
      "blobs_url": "https://api.github.com/repos/ivankelly/bookkeeper/git/blobs{/sha}",
      "git_tags_url": "https://api.github.com/repos/ivankelly/bookkeeper/git/tags{/sha}",
      "git_refs_url": "https://api.github.com/repos/ivankelly/bookkeeper/git/refs{/sha}",
      "trees_url": "https://api.github.com/repos/ivankelly/bookkeeper/git/trees{/sha}",
      "statuses_url": "https://api.github.com/repos/ivankelly/bookkeeper/statuses/{sha}",
      "languages_url": "https://api.github.com/repos/ivankelly/bookkeeper/languages",
      "stargazers_url": "https://api.github.com/repos/ivankelly/bookkeeper/stargazers",
      "contributors_url": "https://api.github.com/repos/ivankelly/bookkeeper/contributors",
      "subscribers_url": "https://api.github.com/repos/ivankelly/bookkeeper/subscribers",
      "subscription_url": "https://api.github.com/repos/ivankelly/bookkeeper/subscription",
      "commits_url": "https://api.github.com/repos/ivankelly/bookkeeper/commits{/sha}",
      "git_commits_url": "https://api.github.com/repos/ivankelly/bookkeeper/git/commits{/sha}",
      "comments_url": "https://api.github.com/repos/ivankelly/bookkeeper/comments{/number}",
      "issue_comment_url": "https://api.github.com/repos/ivankelly/bookkeeper/issues/comments{/number}",
      "contents_url": "https://api.github.com/repos/ivankelly/bookkeeper/contents/{+path}",
      "compare_url": "https://api.github.com/repos/ivankelly/bookkeeper/compare/{base}...{head}",
      "merges_url": "https://api.github.com/repos/ivankelly/bookkeeper/merges",
      "archive_url": "https://api.github.com/repos/ivankelly/bookkeeper/{archive_format}{/ref}",
      "downloads_url": "https://api.github.com/repos/ivankelly/bookkeeper/downloads",
      "issues_url": "https://api.github.com/repos/ivankelly/bookkeeper/issues{/number}",
      "pulls_url": "https://api.github.com/repos/ivankelly/bookkeeper/pulls{/number}",
      "milestones_url": "https://api.github.com/repos/ivankelly/bookkeeper/milestones{/number}",
      "notifications_url": "https://api.github.com/repos/ivankelly/bookkeeper/notifications{?since,all,participating}",
      "labels_url": "https://api.github.com/repos/ivankelly/bookkeeper/labels{/name}",
      "releases_url": "https://api.github.com/repos/ivankelly/bookkeeper/releases{/id}",
      "deployments_url": "https://api.github.com/repos/ivankelly/bookkeeper/deployments",
      "created_at": "2011-04-08T14:13:36Z",
      "updated_at": "2017-11-02T10:28:23Z",
      "pushed_at": "2020-04-06T11:40:14Z",
      "git_url": "git://github.com/ivankelly/bookkeeper.git",
      "ssh_url": "git@github.com:ivankelly/bookkeeper.git",
      "clone_url": "https://github.com/ivankelly/bookkeeper.git",
      "svn_url": "https://github.com/ivankelly/bookkeeper",
      "homepage": null,
      "size": 26206,
      "stargazers_count": 4,
      "watchers_count": 4,
      "language": "Java",
      "has_issues": false,
      "has_projects": true,
      "has_downloads": true,
      "has_wiki": false,
      "has_pages": false,
      "has_discussions": false,
      "forks_count": 2,
      "mirror_url": null,
      "archived": false,
      "disabled": false,
      "open_issues_count": 2,
      "license": {
        "key": "apache-2.0",
        "name": "Apache License 2.0",
        "spdx_id": "Apache-2.0",
        "url": "https://api.github.com/licenses/apache-2.0",
        "node_id": "MDc6TGljZW5zZTI="
      },
      "allow_forking": true,
      "is_template": false,
      "web_commit_signoff_required": false,
      "topics": [],
      "visibility": "public",
      "forks": 2,
      "open_issues": 2,
      "watchers": 4,
      "default_branch": "master"
    }
  },
  "base": {
    "label": "apache:master",
    "ref": "master",
    "sha": "f39c423c8d2c493343e1172a81484c50c1b71168",
    "user": {
      "login": "apache",
      "id": 47359,
      "node_id": "MDEyOk9yZ2FuaXphdGlvbjQ3MzU5",
      "avatar_url": "https://avatars.githubusercontent.com/u/47359?v=4",
      "gravatar_id": "",
      "url": "https://api.github.com/users/apache",
      "html_url": "https://github.com/apache",
      "followers_url": "https://api.github.com/users/apache/followers",
      "following_url": "https://api.github.com/users/apache/following{/other_user}",
      "gists_url": "https://api.github.com/users/apache/gists{/gist_id}",
      "starred_url": "https://api.github.com/users/apache/starred{/owner}{/repo}",
      "subscriptions_url": "https://api.github.com/users/apache/subscriptions",
      "organizations_url": "https://api.github.com/users/apache/orgs",
      "repos_url": "https://api.github.com/users/apache/repos",
      "events_url": "https://api.github.com/users/apache/events{/privacy}",
      "received_events_url": "https://api.github.com/users/apache/received_events",
      "type": "Organization",
      "site_admin": false
    },
    "repo": {
      "id": 1575956,
      "node_id": "MDEwOlJlcG9zaXRvcnkxNTc1OTU2",
      "name": "bookkeeper",
      "full_name": "apache/bookkeeper",
      "private": false,
      "owner": {
        "login": "apache",
        "id": 47359,
        "node_id": "MDEyOk9yZ2FuaXphdGlvbjQ3MzU5",
        "avatar_url": "https://avatars.githubusercontent.com/u/47359?v=4",
        "gravatar_id": "",
        "url": "https://api.github.com/users/apache",
        "html_url": "https://github.com/apache",
        "followers_url": "https://api.github.com/users/apache/followers",
        "following_url": "https://api.github.com/users/apache/following{/other_user}",
        "gists_url": "https://api.github.com/users/apache/gists{/gist_id}",
        "starred_url": "https://api.github.com/users/apache/starred{/owner}{/repo}",
        "subscriptions_url": "https://api.github.com/users/apache/subscriptions",
        "organizations_url": "https://api.github.com/users/apache/orgs",
        "repos_url": "https://api.github.com/users/apache/repos",
        "events_url": "https://api.github.com/users/apache/events{/privacy}",
        "received_events_url": "https://api.github.com/users/apache/received_events",
        "type": "Organization",
        "site_admin": false
      },
      "html_url": "https://github.com/apache/bookkeeper",
      "description": "Apache BookKeeper - a scalable, fault tolerant and low latency storage service optimized for append-only workloads",
      "fork": false,
      "url": "https://api.github.com/repos/apache/bookkeeper",
      "forks_url": "https://api.github.com/repos/apache/bookkeeper/forks",
      "keys_url": "https://api.github.com/repos/apache/bookkeeper/keys{/key_id}",
      "collaborators_url": "https://api.github.com/repos/apache/bookkeeper/collaborators{/collaborator}",
      "teams_url": "https://api.github.com/repos/apache/bookkeeper/teams",
      "hooks_url": "https://api.github.com/repos/apache/bookkeeper/hooks",
      "issue_events_url": "https://api.github.com/repos/apache/bookkeeper/issues/events{/number}",
      "events_url": "https://api.github.com/repos/apache/bookkeeper/events",
      "assignees_url": "https://api.github.com/repos/apache/bookkeeper/assignees{/user}",
      "branches_url": "https://api.github.com/repos/apache/bookkeeper/branches{/branch}",
      "tags_url": "https://api.github.com/repos/apache/bookkeeper/tags",
      "blobs_url": "https://api.github.com/repos/apache/bookkeeper/git/blobs{/sha}",
      "git_tags_url": "https://api.github.com/repos/apache/bookkeeper/git/tags{/sha}",
      "git_refs_url": "https://api.github.com/repos/apache/bookkeeper/git/refs{/sha}",
      "trees_url": "https://api.github.com/repos/apache/bookkeeper/git/trees{/sha}",
      "statuses_url": "https://api.github.com/repos/apache/bookkeeper/statuses/{sha}",
      "languages_url": "https://api.github.com/repos/apache/bookkeeper/languages",
      "stargazers_url": "https://api.github.com/repos/apache/bookkeeper/stargazers",
      "contributors_url": "https://api.github.com/repos/apache/bookkeeper/contributors",
      "subscribers_url": "https://api.github.com/repos/apache/bookkeeper/subscribers",
      "subscription_url": "https://api.github.com/repos/apache/bookkeeper/subscription",
      "commits_url": "https://api.github.com/repos/apache/bookkeeper/commits{/sha}",
      "git_commits_url": "https://api.github.com/repos/apache/bookkeeper/git/commits{/sha}",
      "comments_url": "https://api.github.com/repos/apache/bookkeeper/comments{/number}",
      "issue_comment_url": "https://api.github.com/repos/apache/bookkeeper/issues/comments{/number}",
      "contents_url": "https://api.github.com/repos/apache/bookkeeper/contents/{+path}",
      "compare_url": "https://api.github.com/repos/apache/bookkeeper/compare/{base}...{head}",
      "merges_url": "https://api.github.com/repos/apache/bookkeeper/merges",
      "archive_url": "https://api.github.com/repos/apache/bookkeeper/{archive_format}{/ref}",
      "downloads_url": "https://api.github.com/repos/apache/bookkeeper/downloads",
      "issues_url": "https://api.github.com/repos/apache/bookkeeper/issues{/number}",
      "pulls_url": "https://api.github.com/repos/apache/bookkeeper/pulls{/number}",
      "milestones_url": "https://api.github.com/repos/apache/bookkeeper/milestones{/number}",
      "notifications_url": "https://api.github.com/repos/apache/bookkeeper/notifications{?since,all,participating}",
      "labels_url": "https://api.github.com/repos/apache/bookkeeper/labels{/name}",
      "releases_url": "https://api.github.com/repos/apache/bookkeeper/releases{/id}",
      "deployments_url": "https://api.github.com/repos/apache/bookkeeper/deployments",
      "created_at": "2011-04-06T07:00:07Z",
      "updated_at": "2022-12-26T08:35:33Z",
      "pushed_at": "2022-12-26T11:38:04Z",
      "git_url": "git://github.com/apache/bookkeeper.git",
      "ssh_url": "git@github.com:apache/bookkeeper.git",
      "clone_url": "https://github.com/apache/bookkeeper.git",
      "svn_url": "https://github.com/apache/bookkeeper",
      "homepage": "https://bookkeeper.apache.org/",
      "size": 83255,
      "stargazers_count": 1671,
      "watchers_count": 1671,
      "language": "Java",
      "has_issues": true,
      "has_projects": true,
      "has_downloads": true,
      "has_wiki": false,
      "has_pages": false,
      "has_discussions": false,
      "forks_count": 773,
      "mirror_url": null,
      "archived": false,
      "disabled": false,
      "open_issues_count": 453,
      "license": {
        "key": "apache-2.0",
        "name": "Apache License 2.0",
        "spdx_id": "Apache-2.0",
        "url": "https://api.github.com/licenses/apache-2.0",
        "node_id": "MDc6TGljZW5zZTI="
      },
      "allow_forking": true,
      "is_template": false,
      "web_commit_signoff_required": false,
      "topics": [
        "big-data",
        "bookkeeper"
      ],
      "visibility": "public",
      "forks": 773,
      "open_issues": 453,
      "watchers": 1671,
      "default_branch": "master"
    }
  },
  "_links": {
    "self": {
      "href": "https://api.github.com/repos/apache/bookkeeper/pulls/888"
    },
    "html": {
      "href": "https://github.com/apache/bookkeeper/pull/888"
    },
    "issue": {
      "href": "https://api.github.com/repos/apache/bookkeeper/issues/888"
    },
    "comments": {
      "href": "https://api.github.com/repos/apache/bookkeeper/issues/888/comments"
    },
    "review_comments": {
      "href": "https://api.github.com/repos/apache/bookkeeper/pulls/888/comments"
    },
    "review_comment": {
      "href": "https://api.github.com/repos/apache/bookkeeper/pulls/comments{/number}"
    },
    "commits": {
      "href": "https://api.github.com/repos/apache/bookkeeper/pulls/888/commits"
    },
    "statuses": {
      "href": "https://api.github.com/repos/apache/bookkeeper/statuses/e1c8d6edfc3f31f6a95195f72594d383011b8de9"
    }
  },
  "author_association": "CONTRIBUTOR",
  "auto_merge": null,
  "active_lock_reason": null,
  "merged": false,
  "mergeable": null,
  "rebaseable": null,
  "mergeable_state": "unknown",
  "merged_by": null,
  "comments": 42,
  "review_comments": 53,
  "maintainer_can_modify": false,
  "commits": 22,
  "additions": 2147,
  "deletions": 943,
  "changed_files": 32
}